pyapplication/__init__.py
pyapplication/pyapplication.py
pyapplication-0.0.1.dist-info/LICENSE
pyapplication-0.0.1.dist-info/METADATA
pyapplication-0.0.1.dist-info/WHEEL
pyapplication-0.0.1.dist-info/top_level.txt
pyapplication-0.0.1.dist-info/RECORD
