Metadata-Version: 2.1
Name: pyapplication
Version: 0.0.1
Summary: Application creation package
Home-page: UNKNOWN
Author: Lewis Fulterer
Author-email: lewisfulterer@gmail.com
License: UNKNOWN
Platform: UNKNOWN
Classifier: Programming Language :: Python :: 3
Classifier: License :: OSI Approved :: MIT License
Classifier: Operating System :: OS Independent
Requires-Python: >=3.6
License-File: LICENSE
